binheat.py
binheat-0.2.2.dist-info/METADATA
binheat-0.2.2.dist-info/WHEEL
binheat-0.2.2.dist-info/entry_points.txt
binheat-0.2.2.dist-info/licenses/LICENSE
binheat-0.2.2.dist-info/RECORD
