Metadata-Version: 2.1
Name: binheat
Version: 0.2.2
Summary: Binary heat map generator
Project-URL: Source Code, https://github.com/jwodder/binheat
Project-URL: Bug Tracker, https://github.com/jwodder/binheat/issues
Author-email: John Thorvald Wodder II <binheat@varonathe.org>
License-Expression: MIT
License-File: LICENSE
Keywords: binary heat map,heat map,pdf
Classifier: Environment :: Console
Classifier: License :: OSI Approved :: MIT License
Classifier: Programming Language :: Python :: 3
Classifier: Programming Language :: Python :: 3 :: Only
Classifier: Programming Language :: Python :: 3.7
Classifier: Programming Language :: Python :: 3.8
Classifier: Programming Language :: Python :: 3.9
Classifier: Programming Language :: Python :: 3.10
Classifier: Programming Language :: Python :: 3.11
Classifier: Programming Language :: Python :: 3.12
Classifier: Programming Language :: Python :: Implementation :: CPython
Classifier: Programming Language :: Python :: Implementation :: PyPy
Classifier: Topic :: Multimedia :: Graphics
Requires-Python: >=3.7
Requires-Dist: click>=7.0
Requires-Dist: reportlab~=3.4
